mlops_ods/__init__.py
mlops_ods/app/__init__.py
mlops_ods/app/example.py
mlops_ods/conf/config.yaml
mlops_ods/conf/features/features.yaml
mlops_ods/conf/model/fast.yaml
mlops_ods/conf/model/slow.yaml
mlops_ods/conf/settings/predict.yaml
mlops_ods/conf/settings/train.yaml
mlops_ods/config.py
mlops_ods/dataset/.gitignore
mlops_ods/dataset/2015-street-tree-census-tree-data.csv.dvc
mlops_ods/dataset/features/.gitignore
mlops_ods/dataset/prepared/.gitignore
mlops_ods/dataset/processed/.gitignore
mlops_ods/dvc_functions/__init__.py
mlops_ods/dvc_functions/__main__.py
mlops_ods/dvc_functions/cli.py
mlops_ods/dvc_functions/dvc-research.md
mlops_ods/dvc_functions/models.py
mlops_ods/dvc_functions/preprocessing.py
mlops_ods/dvc_functions/scaler.py
mlops_ods/models/.gitignore
mlops_ods/notebooks/eda.ipynb
mlops_ods/notebooks/model.ipynb
mlops_ods/snakemake_scripts/dag.svg
mlops_ods/snakemake_scripts/model_fit.py
mlops_ods/snakemake_scripts/model_fit_bigger.py
mlops_ods/snakemake_scripts/preprocess_data_base.py
mlops_ods/snakemake_scripts/preprocess_data_research.py
mlops_ods/snakemake_scripts/snakemake_steps.md
mlops_ods/train.py
mlops_ods/train_predict.py
mlops_ods/utils/__init__.py
mlops_ods/utils/utils_etl.py
mlops_ods/utils/utils_model.py
mlops_ods-0.1.202406281646.dist-info/METADATA
mlops_ods-0.1.202406281646.dist-info/WHEEL
mlops_ods-0.1.202406281646.dist-info/RECORD
